immutable/__init__.py
immutable/immutable.py
immutable_config-1.0.dist-info/LICENSE
immutable_config-1.0.dist-info/METADATA
immutable_config-1.0.dist-info/WHEEL
immutable_config-1.0.dist-info/top_level.txt
immutable_config-1.0.dist-info/RECORD
