Metadata-Version: 2.1
Name: immutable-config
Version: 1.0
Summary: Create immutable namedtuple from dict
Home-page: https://github.com/dduraipandian/immutable
Author: Durai Pandian
Author-email: dduraipandian@gmail.com
License: UNKNOWN
Keywords: immutable,frozendict,frozenset,frozenlist
Platform: UNKNOWN
Classifier: Programming Language :: Python
Classifier: License :: OSI Approved :: MIT License
Classifier: Natural Language :: English
Classifier: Intended Audience :: Developers
Classifier: Operating System :: OS Independent
Requires-Python: >=3.6
License-File: LICENSE
